avilla/spec/qq/elements.py
avilla_spec_qq-1.0.0a5.dist-info/WHEEL
avilla_spec_qq-1.0.0a5.dist-info/METADATA
avilla_spec_qq-1.0.0a5.dist-info/licenses/LICENSE
avilla_spec_qq-1.0.0a5.dist-info/RECORD
