Metadata-Version: 2.1
Name: avilla-spec-qq
Version: 1.0.0-alpha.5
License: MIT
Author-email: GreyElaina <GreyElaina@outlook.com>,BlueGlassBlock <blueglassblock@outlook.com>,ProgramRipper <programripper@foxmail.com>,RF-Tar-Railt <rf_tar_railt@qq.com>
Requires-Python: >=3.9
Project-URL: homepage, https://github.com/GraiaProject/Avilla
Project-URL: repository, https://github.com/GraiaProject/Avilla
